load_settings/__init__.py
load_settings/loader.py
load_settings-0.1.dist-info/METADATA
load_settings-0.1.dist-info/WHEEL
load_settings-0.1.dist-info/top_level.txt
load_settings-0.1.dist-info/RECORD
